./.gitignore
./PKG-INFO
./README.md
./pyproject.toml
./vision_agents/plugins/fish/__init__.py
./vision_agents/plugins/fish/stt.py
./vision_agents/plugins/fish/tts.py
vision_agents/plugins/fish/__init__.py
vision_agents/plugins/fish/stt.py
vision_agents/plugins/fish/tts.py
vision_agents_plugins_fish-0.2.10.dist-info/METADATA
vision_agents_plugins_fish-0.2.10.dist-info/WHEEL
vision_agents_plugins_fish-0.2.10.dist-info/RECORD
