Metadata-Version: 2.4
Name: vision-agents-plugins-fish
Version: 0.2.10
Summary: Fish Audio TTS and STT integration for Vision Agents
Project-URL: Documentation, https://visionagents.ai/
Project-URL: Website, https://visionagents.ai/
Project-URL: Source, https://github.com/GetStream/Vision-Agents
License-Expression: MIT
Keywords: AI,STT,TTS,agents,fish-audio,speech-to-text,text-to-speech,voice agents
Requires-Python: >=3.10
Requires-Dist: fish-audio-sdk>=2025.4.2
Requires-Dist: vision-agents
